{
	"@metadata": {
		"name": "bit32",
		"comment": "The library is not imported as default, it is \"required\", and can not be properly identified unless intellisense is active. This is nearly always named as \"bit32\", so it is pretty safe to assume it can be used as prefix.",
		"authors": [
			"Jeblad"
		]
	},
	"bit32 001": {
		"prefix": "bit32.band( ... )",
		"body": [
			"bit32.band( ${1:...} )$0"
		],
		"description": "Bitwise \"and\" of all arguments.\n"
	},
	"bit32 002": {
		"prefix": "bit32.bnot( ... )",
		"body": [
			"bit32.bnot( ${1:x} )$0"
		],
		"description": "Bitwise complement of argument.\n"
	},
	"bit32 003": {
		"prefix": "bit32.bor( ... )",
		"body": [
			"bit32.bor( ${1:...} )$0"
		],
		"description": "Bitwise \"or\" of all arguments.\n"
	},
	"bit32 004": {
		"prefix": "bit32.btest( ... )",
		"body": [
			"bit32.btest( ${1:...} )$0"
		],
		"description": "Bitwise \"and\" of all arguments followed by not equal to zero.\n"
	},
	"bit32 005": {
		"prefix": "bit32.bxor( ... )",
		"body": [
			"bit32.bxor( ${1:...} )$0"
		],
		"description": "Bitwise \"xor\" of all arguments.\n"
	},
	"bit32 006": {
		"prefix": "bit32.extract( n, field, width)",
		"body": [
			"bit32.extract( ${1:n}, ${2:field}${3:, ${4:width}} )$0"
		],
		"description": "Bitwise extract.\n"
	},
	"bit32 007": {
		"prefix": "bit32.replace( n, v, field, width)",
		"body": [
			"bit32.replace( ${1:n}, ${2:v}, ${3:field}${4:, ${5:width}} )$0"
		],
		"description": "Bitwise replace, "
	},
	"bit32 008": {
		"prefix": "bit32.lshift( n, disp )",
		"body": [
			"bit32.lshift( ${1:n}, ${2:disp} )$0"
		],
		"description": "Bitwise left shift.\n"
	},
	"bit32 009": {
		"prefix": "bit32.rshift( n, disp )",
		"body": [
			"bit32.rshift( ${1:n}, ${2:disp} )$0"
		],
		"description": "Bitwise right shift.\n"
	},
	"bit32 010": {
		"prefix": "bit32.arshift( n, disp )",
		"body": [
			"bit32.arshift( ${1:n}, ${2:disp} )$0"
		],
		"description": "Bitwise arithmetic shift.\n"
	},
	"bit32 011": {
		"prefix": "bit32.lrotate( n, disp )",
		"body": [
			"bit32.lrotate( ${1:n}, ${2:disp} )$0"
		],
		"description": "Bitwise left rotate.\n"
	},
	"bit32 012": {
		"prefix": "bit32.rrotate( n, disp )",
		"body": [
			"bit32.rrotate( ${1:n}, ${2:disp} )$0"
		],
		"description": "Bitwise right rotate.\n"
	}
}